asct/__init__.py
asct/optimize_cell.py
asct/src/Cell.py
asct/src/Optimizer.py
asct/src/SummaryNet.py
asct/src/Tuner.py
asct/src/__init__.py
asct-0.0.5.dist-info/LICENSE.md
asct-0.0.5.dist-info/METADATA
asct-0.0.5.dist-info/WHEEL
asct-0.0.5.dist-info/entry_points.txt
asct-0.0.5.dist-info/top_level.txt
asct-0.0.5.dist-info/RECORD
