Metadata-Version: 2.1
Name: asct
Version: 0.0.5
Summary: Automated Single Cell Tuner
Home-page: https://github.com/pbcanfield/ASCT
Author: Pete Canfield
Author-email: pbczgf@umsystem.edu
License: MIT
Platform: UNKNOWN
Classifier: Intended Audience :: Developers
Classifier: Intended Audience :: Education
Classifier: Intended Audience :: Science/Research
Classifier: License :: OSI Approved :: MIT License
Classifier: Programming Language :: Python :: 3.7
Classifier: Topic :: Software Development :: Libraries
Classifier: Topic :: Software Development :: Libraries :: Python Modules
Classifier: Operating System :: OS Independent
Requires-Dist: sbi
Requires-Dist: neuron
Requires-Dist: numpy
Requires-Dist: scipy
Requires-Dist: torch
Requires-Dist: tqdm
